cclm/__init__.py
cclm/augmentation/__init__.py
cclm/models.py
cclm/preprocessing.py
cclm/pretrainers/__init__.py
cclm/pretrainers/causal_lm.py
cclm/pretrainers/cl_mask_pretrainer.py
cclm/pretrainers/core.py
cclm/pretrainers/masked_language_modeling.py
cclm/shelf/__init__.py
cclm-0.1.2.dist-info/LICENSE
cclm-0.1.2.dist-info/WHEEL
cclm-0.1.2.dist-info/METADATA
cclm-0.1.2.dist-info/RECORD
